Metadata-Version: 2.1
Name: ai_is_odd
Version: 0.1.1
Summary: A super AI-powered library to determine if number is odd or odd with power of AI
Home-page: https://github.com/arturshevchenko/ai_is_odd
Author: Artur Shevchenko
Author-email: artur.shev8@gmail.com
License: MIT
Keywords: AI,EVEN,ODD
Classifier: Programming Language :: Python :: 3
Classifier: License :: OSI Approved :: MIT License
Classifier: Operating System :: OS Independent
Requires-Python: >=3.6
License-File: LICENSE
Requires-Dist: requests==2.32.3
Requires-Dist: python-dotenv==1.0.1
Requires-Dist: certifi==2024.8.30
Requires-Dist: charset-normalizer==3.4.0
Requires-Dist: idna==3.10
Requires-Dist: urllib3==2.2.3
